rm_sdk_python/__init__.py
tests/__init__.py
tests/api_test.py
rm_sdk_python-1.0.4.dist-info/METADATA
rm_sdk_python-1.0.4.dist-info/WHEEL
rm_sdk_python-1.0.4.dist-info/top_level.txt
rm_sdk_python-1.0.4.dist-info/RECORD
