Metadata-Version: 2.1
Name: rm-sdk-python
Version: 1.0.4
Summary: The Official Resellme Python SDK .
Home-page: https://github.com/bevennyamande/rm-sdk-python/
Author: Beven Nyamande aka 0xbeven
Author-email: bevenfx@gmail.com
License: MIT
Project-URL: Homepage, https://github.com/bevennyamande/rm-sdk-python/
Project-URL: Bug Tracker, https://github.com/bevennyamande/rm-sdk-python/issues
Classifier: License :: OSI Approved :: MIT License
Classifier: Programming Language :: Python :: 3
Classifier: Operating System :: OS Independent
Requires-Python: >=3.6
Requires-Dist: requests
